LICENSE
MANIFEST.in
README.rst
setup.cfg
setup.py
bpc8583/ISO8583.py
bpc8583/__init__.py
bpc8583/card.py
bpc8583/spec.py
bpc8583/terminal.py
bpc8583/tools.py
bpc8583/transaction.py
bpc8583.egg-info/PKG-INFO
bpc8583.egg-info/SOURCES.txt
bpc8583.egg-info/dependency_links.txt
bpc8583.egg-info/requires.txt
bpc8583.egg-info/top_level.txt
bpc8583.egg-info/zip-safe