Metadata-Version: 1.1
Name: bpc8583
Version: 1.60
Summary: ISO8583 library and tools (BPC's flavour)
Home-page: https://github.com/timgabets/bpc8583
Author: Tim Gabets
Author-email: tim@gabets.ru
License: LGPLv2
Keywords: POS ISO8583 banking financial payment
Platform: UNKNOWN
Classifier: License :: OSI Approved :: GNU Lesser General Public License v2 (LGPLv2)
Classifier: Operating System :: OS Independent
Classifier: Programming Language :: Python :: 3
Classifier: Programming Language :: Python :: 3.3
Classifier: Programming Language :: Python :: 3.4
Classifier: Programming Language :: Python :: 3.5
Classifier: Topic :: Communications
Classifier: Intended Audience :: Developers
